mlatex/__init__.py
mlatex-0.1.2.dist-info/METADATA
mlatex-0.1.2.dist-info/WHEEL
mlatex-0.1.2.dist-info/top_level.txt
mlatex-0.1.2.dist-info/RECORD
