Metadata-Version: 2.1
Name: mlatex
Version: 0.1.2
Summary: This is a library designed to write simple latex files
Home-page: UNKNOWN
Author: Steve Mohr
Author-email: steve.h.mohr@gmail.com
License: UNKNOWN
Platform: UNKNOWN
